pve_cli/__init__.py
pve_cli/cluster_cmd.py
pve_cli/guest_cmd.py
pve_cli/helper/__init__.py
pve_cli/helper/check.py
pve_cli/helper/conversion.py
pve_cli/helper/migration.py
pve_cli/helper/ui.py
pve_cli/main.py
pve_cli/proxmox/__init__.py
pve_cli/proxmox/api.py
pve_cli/proxmox/exceptions.py
pve_cli/proxmox/node.py
pve_cli/proxmox/permissions.py
pve_cli/proxmox/types.py
pve_cli/proxmox/vm.py
pve_cli/util/__init__.py
pve_cli/util/callbacks.py
pve_cli/util/completion.py
pve_cli/util/constants.py
pve_cli/util/exceptions.py
pve_cli/util/validators.py
pve_cli/vm_cmd.py
pve_cli-0.10.1.dist-info/WHEEL
pve_cli-0.10.1.dist-info/entry_points.txt
pve_cli-0.10.1.dist-info/METADATA
pve_cli-0.10.1.dist-info/RECORD
