Metadata-Version: 2.3
Name: pve-cli
Version: 0.10.1
Summary: CLI Tool to manage VMs and more on proxmox clusters
Author: Dominik Rimpf
Author-email: Dominik Rimpf <dev@drimpf.de>
Classifier: Development Status :: 5 - Production/Stable
Classifier: License :: OSI Approved :: Mozilla Public License 2.0 (MPL 2.0)
Classifier: Programming Language :: Python :: 3
Classifier: Programming Language :: Python :: 3.9
Classifier: Programming Language :: Python :: 3.10
Classifier: Programming Language :: Python :: 3.11
Classifier: Programming Language :: Python :: 3.12
Requires-Dist: packaging>=25.0,<26.0
Requires-Dist: proxmoxer>=2.2.0,<3.0.0
Requires-Dist: requests>=2.32.5,<3.0.0
Requires-Dist: requests-toolbelt>=1.0.0,<2.0.0
Requires-Dist: toml>=0.10.2,<0.11.0
Requires-Dist: typer-slim[standard]>=0.19.2,<0.20.0
Requires-Python: >=3.9, <4.0.0
Project-URL: Source code, https://gitlab.com/domrim/pve-cli
